flask_compress/__init__.py
flask_compress/_version.py
flask_compress/compat.py
flask_compress/flask_compress.py
flask_compress-1.22.dist-info/licenses/LICENSE.txt
flask_compress-1.22.dist-info/METADATA
flask_compress-1.22.dist-info/WHEEL
flask_compress-1.22.dist-info/top_level.txt
flask_compress-1.22.dist-info/RECORD
