Metadata-Version: 2.4
Name: Flask-Compress
Version: 1.22
Summary: Compress responses in your Flask app with gzip, deflate, brotli or zstandard.
Home-page: https://github.com/colour-science/flask-compress
Author: Thomas Mansencal
Author-email: thomas.mansencal@gmail.com
License: MIT
Platform: any
Classifier: Environment :: Web Environment
Classifier: Intended Audience :: Developers
Classifier: License :: OSI Approved :: MIT License
Classifier: Operating System :: OS Independent
Classifier: Programming Language :: Python :: 3.9
Classifier: Programming Language :: Python :: 3.10
Classifier: Programming Language :: Python :: 3.11
Classifier: Programming Language :: Python :: 3.12
Classifier: Programming Language :: Python :: 3.13
Classifier: Programming Language :: Python :: 3.14
Classifier: Programming Language :: Python :: Implementation :: CPython
Classifier: Programming Language :: Python :: Implementation :: PyPy
Classifier: Topic :: Internet :: WWW/HTTP :: Dynamic Content
Classifier: Topic :: Software Development :: Libraries :: Python Modules
Requires-Python: >=3.9
License-File: LICENSE.txt
Requires-Dist: flask
Requires-Dist: brotli; platform_python_implementation != "PyPy"
Requires-Dist: brotlicffi; platform_python_implementation == "PyPy"
Requires-Dist: backports.zstd; python_version < "3.14"
Dynamic: author
Dynamic: author-email
Dynamic: classifier
Dynamic: description
Dynamic: description-content-type
Dynamic: home-page
Dynamic: license
Dynamic: license-file
Dynamic: platform
Dynamic: requires-dist
Dynamic: requires-python
Dynamic: summary
